README.md
setup.py
cve/__init__.py
cve/command.py
cve/society2.py
cve/society3.py
cve.egg-info/PKG-INFO
cve.egg-info/SOURCES.txt
cve.egg-info/dependency_links.txt
cve.egg-info/entry_points.txt
cve.egg-info/top_level.txt