Metadata-Version: 2.1
Name: cve
Version: 1.0.1
Summary: core socialist values encoding
Home-page: https://github.com/feng409/core-values-encoder
Author: chemf
Author-email: eoyohe@gmail.com
License: UNKNOWN
Platform: UNKNOWN
